CHANGELOG.txt
LICENCE.txt
MANIFEST.in
README.txt
setup.cfg
setup.py
timestramp/__init__.py
timestramp/keys.json
timestramp.egg-info/PKG-INFO
timestramp.egg-info/SOURCES.txt
timestramp.egg-info/dependency_links.txt
timestramp.egg-info/top_level.txt