Metadata-Version: 2.1
Name: timestramp
Version: 0.0.5
Home-page: 
Author: Maaz Hussain
Author-email: maazhussain7373@gmail.com
License: MIT
Classifier: Development Status :: 5 - Production/Stable
Classifier: Intended Audience :: Education
Classifier: Operating System :: Microsoft :: Windows :: Windows 10
Classifier: License :: OSI Approved :: MIT License
Classifier: Programming Language :: Python :: 3
License-File: LICENCE.txt
